[
{"source_id": 7, "location_name": "UPenn", "url": "https://order.sweetgreen.com/upenn/menu", "phone_number": "12153861365", "street_address_1": "3925 Walnut St", "street_address_2": "", "city": "Philadelphia", "postal_code": "19104", "state": "PA", "country": "US", "latitude": 39.954343, "longitude": -75.201455, "schedules": [{"sunday": "10:30 AM - 07:00 PM", "monday": "10:30 AM - 10:00 PM", "tuesday": "10:30 AM - 10:00 PM", "wednesday": "10:30 AM - 10:00 PM", "thursday": "10:30 AM - 04:00 PM", "friday": "10:30 AM - 07:00 PM", "saturday": "10:30 AM - 07:00 PM"}]},
{"source_id": 4, "location_name": "Reston", "url": "https://order.sweetgreen.com/reston/menu", "phone_number": "15712030082", "street_address_1": "1824 Library St", "street_address_2": "", "city": "Reston", "postal_code": "20190", "state": "VA", "country": "US", "latitude": 38.95834, "longitude": -77.359482, "schedules": [{"sunday": "10:30 AM - 08:00 PM", "monday": "10:30 AM - 10:00 PM", "tuesday": "10:30 AM - 10:00 PM", "wednesday": "10:30 AM - 10:00 PM", "thursday": "10:30 AM - 08:00 PM", "friday": "10:30 AM - 08:00 PM", "saturday": "10:30 AM - 09:00 PM"}]},
{"source_id": 3, "location_name": "Capitol Hill", "url": "https://order.sweetgreen.com/capitol-hill/menu", "phone_number": "12025479338", "street_address_1": "221 Pennsylvania Ave SE", "street_address_2": "", "city": "Washington", "postal_code": "20003", "state": "DC", "country": "US", "latitude": 38.88696, "longitude": -77.002758, "schedules": [{"sunday": "10:30 AM - 08:00 PM", "monday": "10:30 AM - 10:00 PM", "tuesday": "10:30 AM - 10:00 PM", "wednesday": "10:30 AM - 10:00 PM", "thursday": "10:30 AM - 08:00 PM", "friday": "10:30 AM - 08:00 PM", "saturday": "10:30 AM - 08:00 PM"}]},
{"source_id": 5, "location_name": "Ballston", "url": "https://order.sweetgreen.com/ballston/menu", "phone_number": "17035222016", "street_address_1": "4075 Wilson Blvd #C", "street_address_2": "", "city": "Arlington", "postal_code": "22203", "state": "VA", "country": "US", "latitude": 38.880192, "longitude": -77.108544, "schedules": [{"sunday": "10:30 AM - 08:00 PM", "monday": "09:30 AM - 10:00 PM", "tuesday": "09:30 AM - 10:00 PM", "wednesday": "09:30 AM - 10:00 PM", "thursday": "09:30 AM - 08:00 PM", "friday": "09:30 AM - 08:00 PM", "saturday": "09:30 AM - 08:00 PM"}]},
{"source_id": 9, "location_name": "19th + L (RETIRED)", "url": "https://order.sweetgreen.com/19th-l-retired/menu", "phone_number": "12023313355", "street_address_1": "1901 L St NW", "street_address_2": "", "city": "Washington", "postal_code": "20036", "state": "DC", "country": "US", "latitude": 38.904038, "longitude": -77.04391, "schedules": [{"monday": "10:30 AM - 08:00 PM", "tuesday": "10:30 AM - 08:00 PM", "wednesday": "10:30 AM - 08:00 PM", "thursday": "10:30 AM - 08:00 PM", "friday": "10:30 AM - 06:00 PM"}]},
{"source_id": 11, "location_name": "Mosaic", "url": "https://order.sweetgreen.com/mosaic/menu", "phone_number": "17039927892", "street_address_1": "2905 District Ave, Ste 185", "street_address_2": "", "city": "Fairfax", "postal_code": "22031", "state": "VA", "country": "US", "latitude": 38.873134, "longitude": -77.229084, "schedules": [{"sunday": "10:30 AM - 08:00 PM", "monday": "10:30 AM - 11:00 PM", "tuesday": "10:30 AM - 11:00 PM", "wednesday": "10:30 AM - 11:00 PM", "thursday": "10:30 AM - 08:00 PM", "friday": "10:30 AM - 08:00 PM", "saturday": "10:30 AM - 08:00 PM"}]},
{"source_id": 10, "location_name": "City Vista (RETIRED)", "url": "https://order.sweetgreen.com/city-vista-retired/menu", "phone_number": "12022894674", "street_address_1": "1065 5th St NW", "street_address_2": "", "city": "Washington", "postal_code": "20001", "state": "DC", "country": "US", "latitude": 38.903233, "longitude": -77.018755, "schedules": [{"sunday": "10:30 AM - 10:00 PM", "monday": "10:30 AM - 10:00 PM", "tuesday": "10:30 AM - 10:00 PM", "wednesday": "10:30 AM - 10:00 PM", "thursday": "10:30 AM - 10:00 PM", "friday": "10:30 AM - 10:00 PM", "saturday": "10:30 AM - 10:00 PM"}]},
{"source_id": 14, "location_name": "NoMad", "url": "https://order.sweetgreen.com/nomad/menu", "phone_number": "16464498884", "street_address_1": "1164 Broadway", "street_address_2": "", "city": "New York", "postal_code": "10001", "state": "NY", "country": "US", "latitude": 40.744905, "longitude": -73.988486, "schedules": [{"sunday": "10:30 AM - 06:00 PM", "monday": "10:30 AM - 10:00 PM", "tuesday": "10:30 AM - 10:00 PM", "wednesday": "10:30 AM - 10:00 PM", "thursday": "10:30 AM - 06:00 PM", "friday": "10:30 AM - 06:00 PM", "saturday": "10:30 AM - 06:00 PM"}]},
{"source_id": 15, "location_name": "Silver Spring", "url": "https://order.sweetgreen.com/silver-spring/menu", "phone_number": "13012445402", "street_address_1": "8517 Georgia Ave", "street_address_2": "", "city": "Silver Spring", "postal_code": "20910", "state": "MD", "country": "US", "latitude": 38.995185, "longitude": -77.026587, "schedules": [{"sunday": "09:30 AM - 07:00 PM", "monday": "09:30 AM - 10:00 PM", "tuesday": "09:30 AM - 10:00 PM", "wednesday": "09:30 AM - 10:00 PM", "thursday": "09:30 AM - 04:00 PM", "friday": "09:30 AM - 07:00 PM", "saturday": "09:30 AM - 07:00 PM"}]},
{"source_id": 13, "location_name": "14th + W", "url": "https://order.sweetgreen.com/14th-w/menu", "phone_number": "12025062956", "street_address_1": "1325 W St NW", "street_address_2": "", "city": "Washington", "postal_code": "20009", "state": "DC", "country": "US", "latitude": 38.919489, "longitude": -77.030934, "schedules": [{"sunday": "10:30 AM - 08:00 PM", "monday": "10:30 AM - 10:00 PM", "tuesday": "10:30 AM - 10:00 PM", "wednesday": "10:30 AM - 10:00 PM", "thursday": "10:30 AM - 08:00 PM", "friday": "10:30 AM - 08:00 PM", "saturday": "10:30 AM - 08:00 PM"}]},
{"source_id": 12, "location_name": "Glover Park", "url": "https://order.sweetgreen.com/glover-park/menu", "phone_number": "12023334307", "street_address_1": "2200 Wisconsin Ave NW", "street_address_2": "", "city": "Washington", "postal_code": "20007", "state": "DC", "country": "US", "latitude": 38.919172, "longitude": -77.071045, "schedules": [{"monday": "10:30 AM - 07:00 PM", "tuesday": "10:30 AM - 07:00 PM", "wednesday": "10:30 AM - 07:00 PM", "thursday": "10:30 AM - 07:00 PM", "friday": "10:30 AM - 07:00 PM"}]},
{"source_id": 17, "location_name": "Tysons Galleria", "url": "https://order.sweetgreen.com/tysons-galleria/menu", "phone_number": "17036390355", "street_address_1": "2001 International Dr", "street_address_2": "", "city": "McLean", "postal_code": "22102", "state": "VA", "country": "US", "latitude": 38.924059, "longitude": -77.225518, "schedules": [{"sunday": "11:00 AM - 06:00 PM", "monday": "10:30 AM - 07:00 PM", "tuesday": "10:30 AM - 07:00 PM", "wednesday": "10:30 AM - 07:00 PM", "thursday": "10:30 AM - 05:00 PM", "friday": "10:30 AM - 05:00 PM", "saturday": "10:30 AM - 07:00 PM"}]},
{"source_id": 18, "location_name": "McLean (RETIRED)", "url": "https://order.sweetgreen.com/mclean-retired/menu", "phone_number": "17039428888", "street_address_1": "6707 Old Dominion Drive", "street_address_2": "", "city": "McLean", "postal_code": "22101", "state": "VA", "country": "US", "latitude": 38.933027, "longitude": -77.176008, "schedules": [{"sunday": "10:30 AM - 09:00 PM", "monday": "10:30 AM - 09:00 PM", "tuesday": "10:30 AM - 09:00 PM", "wednesday": "10:30 AM - 09:00 PM", "thursday": "10:30 AM - 09:00 PM", "friday": "10:30 AM - 09:00 PM", "saturday": "10:30 AM - 09:00 PM"}]},
{"source_id": 16, "location_name": "Back Bay", "url": "https://order.sweetgreen.com/back-bay/menu", "phone_number": "16179363464", "street_address_1": "659 Boylston St", "street_address_2": "", "city": "Boston", "postal_code": "02116", "state": "MA", "country": "US", "latitude": 42.350002, "longitude": -71.078668, "schedules": [{"sunday": "10:30 AM - 10:00 PM", "monday": "09:30 AM - 10:00 PM", "tuesday": "09:30 AM - 10:00 PM", "wednesday": "09:30 AM - 10:00 PM", "thursday": "09:30 AM - 09:00 PM", "friday": "09:30 AM - 09:00 PM", "saturday": "10:30 AM - 10:00 PM"}]},
{"source_id": 2, "location_name": "Bethesda", "url": "https://order.sweetgreen.com/bethesda/menu", "phone_number": "13016547336", "street_address_1": "4831 Bethesda Ave", "street_address_2": "", "city": "Bethesda", "postal_code": "20814", "state": "MD", "country": "US", "latitude": 38.981135, "longitude": -77.096996, "schedules": [{"sunday": "09:30 AM - 08:00 PM", "monday": "09:30 AM - 10:00 PM", "tuesday": "09:30 AM - 10:00 PM", "wednesday": "09:30 AM - 10:00 PM", "thursday": "09:30 AM - 04:00 PM", "friday": "09:30 AM - 08:00 PM", "saturday": "09:30 AM - 08:00 PM"}]},
{"source_id": 19, "location_name": "Fort Point", "url": "https://order.sweetgreen.com/fort-point/menu", "phone_number": "18572637916", "street_address_1": "372 Congress St", "street_address_2": "", "city": "Boston", "postal_code": "02210", "state": "MA", "country": "US", "latitude": 42.349997, "longitude": -71.047618, "schedules": [{"monday": "10:30 AM - 08:00 PM", "tuesday": "10:30 AM - 08:00 PM", "wednesday": "10:30 AM - 08:00 PM", "thursday": "10:30 AM - 08:00 PM", "friday": "10:30 AM - 08:00 PM"}]},
{"source_id": 1, "location_name": "Dupont", "url": "https://order.sweetgreen.com/dupont/menu", "phone_number": "12023879338", "street_address_1": "1512 Connecticut Ave NW", "street_address_2": "", "city": "Washington", "postal_code": "20036", "state": "DC", "country": "US", "latitude": 38.910499, "longitude": -77.044288, "schedules": [{"sunday": "10:30 AM - 08:00 PM", "monday": "10:30 AM - 10:00 PM", "tuesday": "10:30 AM - 10:00 PM", "wednesday": "10:30 AM - 10:00 PM", "thursday": "10:30 AM - 08:00 PM", "friday": "10:30 AM - 08:00 PM", "saturday": "10:30 AM - 08:00 PM"}]},
{"source_id": 20, "location_name": "TriBeCa", "url": "https://order.sweetgreen.com/tribeca/menu", "phone_number": "16469228572", "street_address_1": "413 Greenwich St", "street_address_2": "", "city": "New York", "postal_code": "10013", "state": "NY", "country": "US", "latitude": 40.721335, "longitude": -74.009703, "schedules": [{"monday": "10:30 AM - 04:00 PM", "tuesday": "10:30 AM - 04:00 PM", "wednesday": "10:30 AM - 04:00 PM", "thursday": "10:30 AM - 04:00 PM", "friday": "10:30 AM - 04:00 PM"}]},
{"source_id": 21, "location_name": "10th + Walnut", "url": "https://order.sweetgreen.com/10th-walnut/menu", "phone_number": "12154546770", "street_address_1": "924 Walnut St", "street_address_2": "", "city": "Philadelphia", "postal_code": "19107", "state": "PA", "country": "US", "latitude": 39.948193, "longitude": -75.156172, "schedules": [{"sunday": "10:30 AM - 07:00 PM", "monday": "10:30 AM - 10:00 PM", "tuesday": "10:30 AM - 10:00 PM", "wednesday": "10:30 AM - 10:00 PM", "thursday": "10:30 AM - 04:00 PM", "friday": "10:30 AM - 07:00 PM", "saturday": "10:30 AM - 07:00 PM"}]},
{"source_id": 22, "location_name": "Chestnut Hill", "url": "https://order.sweetgreen.com/chestnut-hill/menu", "phone_number": "16179160788", "street_address_1": "210 Boylston St", "street_address_2": "", "city": "Chestnut Hill", "postal_code": "02467", "state": "MA", "country": "US", "latitude": 42.319485, "longitude": -71.177504, "schedules": [{"sunday": "10:30 AM - 09:00 PM", "monday": "09:30 AM - 10:00 PM", "tuesday": "09:30 AM - 10:00 PM", "wednesday": "09:30 AM - 10:00 PM", "thursday": "09:30 AM - 09:00 PM", "friday": "09:30 AM - 09:00 PM", "saturday": "10:30 AM - 09:00 PM"}]},
{"source_id": 23, "location_name": "Navy Yard", "url": "https://order.sweetgreen.com/navy-yard/menu", "phone_number": "12025547336", "street_address_1": "1212 4th St SE", "street_address_2": "", "city": "Washington", "postal_code": "20003", "state": "DC", "country": "US", "latitude": 38.875191, "longitude": -77.000141, "schedules": [{"sunday": "09:30 AM - 08:00 PM", "monday": "09:30 AM - 10:00 PM", "tuesday": "09:30 AM - 10:00 PM", "wednesday": "09:30 AM - 10:00 PM", "thursday": "09:30 AM - 08:00 PM", "friday": "09:30 AM - 08:00 PM", "saturday": "09:30 AM - 08:00 PM"}]},
{"source_id": 24, "location_name": "Williamsburg", "url": "https://order.sweetgreen.com/williamsburg/menu", "phone_number": "13479873863", "street_address_1": "162 N 4th St", "street_address_2": "", "city": "Brooklyn", "postal_code": "11211", "state": "NY", "country": "US", "latitude": 40.715622, "longitude": -73.958902, "schedules": [{"sunday": "10:30 AM - 10:00 PM", "monday": "10:30 AM - 10:00 PM", "tuesday": "10:30 AM - 10:00 PM", "wednesday": "10:30 AM - 10:00 PM", "thursday": "10:30 AM - 10:00 PM", "friday": "10:30 AM - 10:00 PM", "saturday": "10:30 AM - 10:00 PM"}]},
{"source_id": 25, "location_name": "Nolita", "url": "https://order.sweetgreen.com/nolita/menu", "phone_number": "16469645012", "street_address_1": "100 Kenmare St", "street_address_2": "", "city": "New York", "postal_code": "10012", "state": "NY", "country": "US", "latitude": 40.721046, "longitude": -73.997269, "schedules": [{"sunday": "09:30 AM - 08:00 PM", "monday": "09:30 AM - 10:00 PM", "tuesday": "09:30 AM - 10:00 PM", "wednesday": "09:30 AM - 10:00 PM", "thursday": "09:30 AM - 04:00 PM", "friday": "09:30 AM - 08:00 PM", "saturday": "09:30 AM - 08:00 PM"}]},
{"source_id": 27, "location_name": "Logan Circle", "url": "https://order.sweetgreen.com/logan-circle/menu", "phone_number": "12022347336", "street_address_1": "1461 P St NW", "street_address_2": "", "city": "Washington", "postal_code": "20005", "state": "DC", "country": "US", "latitude": 38.909773, "longitude": -77.033675, "schedules": [{"sunday": "10:30 AM - 08:00 PM", "monday": "10:30 AM - 10:00 PM", "tuesday": "10:30 AM - 10:00 PM", "wednesday": "10:30 AM - 10:00 PM", "thursday": "10:30 AM - 08:00 PM", "friday": "10:30 AM - 08:00 PM", "saturday": "10:30 AM - 08:00 PM"}]},
{"source_id": 26, "location_name": "Georgetown Old", "url": "https://order.sweetgreen.com/georgetown-old/menu", "phone_number": "12023379338", "street_address_1": "3333 M St NW", "street_address_2": "", "city": "Washington", "postal_code": "20007", "state": "DC", "country": "US", "latitude": 38.9053114, "longitude": -77.0673349, "schedules": [{"sunday": "10:30 AM - 10:00 PM", "monday": "10:30 AM - 10:00 PM", "tuesday": "10:30 AM - 10:00 PM", "wednesday": "10:30 AM - 10:00 PM", "thursday": "10:30 AM - 10:00 PM", "friday": "10:30 AM - 10:00 PM", "saturday": "10:30 AM - 10:00 PM"}]},
{"source_id": 29, "location_name": "West End", "url": "https://order.sweetgreen.com/west-end/menu", "phone_number": "12026292100", "street_address_1": "2238 M St NW", "street_address_2": "", "city": "Washington", "postal_code": "20037", "state": "DC", "country": "US", "latitude": 38.90507, "longitude": -77.049308, "schedules": [{"monday": "09:30 AM - 10:00 PM", "tuesday": "09:30 AM - 10:00 PM", "wednesday": "09:30 AM - 10:00 PM"}]},
{"source_id": 28, "location_name": "Ardmore", "url": "https://order.sweetgreen.com/ardmore/menu", "phone_number": "16106429400", "street_address_1": "68 Coulter Ave", "street_address_2": "", "city": "Ardmore", "postal_code": "19003", "state": "PA", "country": "US", "latitude": 40.007757, "longitude": -75.288148, "schedules": [{"sunday": "10:30 AM - 07:00 PM", "monday": "10:30 AM - 10:00 PM", "tuesday": "10:30 AM - 10:00 PM", "wednesday": "10:30 AM - 10:00 PM", "thursday": "10:30 AM - 04:00 PM", "friday": "10:30 AM - 07:00 PM", "saturday": "10:30 AM - 07:00 PM"}]},
{"source_id": 30, "location_name": "West 3rd", "url": "https://order.sweetgreen.com/west-3rd/menu", "phone_number": "13239343404", "street_address_1": "8055 W 3rd St", "street_address_2": "", "city": "Los Angeles", "postal_code": "90048", "state": "CA", "country": "US", "latitude": 34.07229, "longitude": -118.365075, "schedules": [{"sunday": "10:00 AM - 07:00 PM", "monday": "10:00 AM - 10:00 PM", "tuesday": "10:00 AM - 10:00 PM", "wednesday": "10:00 AM - 10:00 PM", "thursday": "10:00 AM - 03:00 PM", "friday": "10:00 AM - 07:00 PM", "saturday": "10:00 AM - 07:00 PM"}]},
{"source_id": 31, "location_name": "Santa Monica", "url": "https://order.sweetgreen.com/santa-monica/menu", "phone_number": "14247448321", "street_address_1": "1343 4th St", "street_address_2": "", "city": "Santa Monica", "postal_code": "90401", "state": "CA", "country": "US", "latitude": 34.017024, "longitude": -118.495628, "schedules": [{"sunday": "10:00 AM - 03:00 PM", "monday": "10:00 AM - 08:00 PM", "tuesday": "10:00 AM - 08:00 PM", "wednesday": "10:00 AM - 08:00 PM", "friday": "10:00 AM - 03:00 PM", "saturday": "10:00 AM - 03:00 PM"}]},
{"source_id": 32, "location_name": "Sweetgreen Brink Demo", "url": "https://order.sweetgreen.com/sweetgreen-brink-demo/menu", "phone_number": "15555555555", "street_address_1": "26 Broadway", "street_address_2": "", "city": "New York", "postal_code": "10004", "state": "NY", "country": "US", "latitude": 40.705572, "longitude": -74.013039, "schedules": [{"sunday": "00:00 AM - 11:45 PM", "monday": "00:00 AM - 11:45 PM", "tuesday": "00:00 AM - 11:45 PM", "wednesday": "00:00 AM - 11:45 PM", "thursday": "00:00 AM - 11:45 PM", "friday": "00:00 AM - 11:45 PM", "saturday": "00:00 AM - 11:45 PM"}]},
{"source_id": 34, "location_name": "Rittenhouse", "url": "https://order.sweetgreen.com/rittenhouse/menu", "phone_number": "12156659710", "street_address_1": "1821 Chestnut St", "street_address_2": "", "city": "Philadelphia", "postal_code": "19103", "state": "PA", "country": "US", "latitude": 39.952061, "longitude": -75.171099, "schedules": [{"sunday": "10:30 AM - 08:00 PM", "monday": "10:30 AM - 10:00 PM", "tuesday": "10:30 AM - 10:00 PM", "wednesday": "10:30 AM - 10:00 PM", "thursday": "10:30 AM - 04:00 PM", "friday": "10:30 AM - 08:00 PM", "saturday": "10:30 AM - 08:00 PM"}]},
{"source_id": 36, "location_name": "Harbor East", "url": "https://order.sweetgreen.com/harbor-east/menu", "phone_number": "14105375006", "street_address_1": "1306 Fleet St", "street_address_2": "", "city": "Baltimore", "postal_code": "21202", "state": "MD", "country": "US", "latitude": 39.284464, "longitude": -76.598593, "schedules": [{"sunday": "09:30 AM - 08:00 PM", "monday": "09:30 AM - 10:00 PM", "tuesday": "09:30 AM - 10:00 PM", "wednesday": "09:30 AM - 10:00 PM", "thursday": "09:30 AM - 04:00 PM", "friday": "09:30 AM - 08:00 PM", "saturday": "09:30 AM - 08:00 PM"}]},
{"source_id": 33, "location_name": "Columbia U", "url": "https://order.sweetgreen.com/columbia-u/menu", "phone_number": "19176756616", "street_address_1": "2937 Broadway", "street_address_2": "", "city": "New York", "postal_code": "10025", "state": "NY", "country": "US", "latitude": 40.807314, "longitude": -73.96474, "schedules": [{"sunday": "09:30 AM - 10:00 PM", "monday": "09:30 AM - 10:00 PM", "tuesday": "09:30 AM - 10:00 PM", "wednesday": "09:30 AM - 10:00 PM", "thursday": "09:30 AM - 08:00 PM", "friday": "09:30 AM - 10:00 PM", "saturday": "09:30 AM - 10:00 PM"}]},
{"source_id": 35, "location_name": "Lynnfield", "url": "https://order.sweetgreen.com/lynnfield/menu", "phone_number": "17813425540", "street_address_1": "675 Market St", "street_address_2": "", "city": "Lynnfield", "postal_code": "01940", "state": "MA", "country": "US", "latitude": 42.515939, "longitude": -71.035666, "schedules": [{"sunday": "09:30 AM - 10:00 PM", "monday": "09:30 AM - 10:00 PM", "tuesday": "09:30 AM - 10:00 PM", "wednesday": "09:30 AM - 10:00 PM", "thursday": "09:30 AM - 08:00 PM", "friday": "09:30 AM - 10:00 PM", "saturday": "09:30 AM - 10:00 PM"}]},
{"source_id": 37, "location_name": "75th + Amsterdam", "url": "https://order.sweetgreen.com/75th-amsterdam/menu", "phone_number": "12124964081", "street_address_1": "311 Amsterdam Ave", "street_address_2": "", "city": "New York", "postal_code": "10023", "state": "NY", "country": "US", "latitude": 40.780286, "longitude": -73.980146, "schedules": [{"sunday": "10:30 AM - 08:00 PM", "monday": "10:30 AM - 10:00 PM", "tuesday": "10:30 AM - 10:00 PM", "wednesday": "10:30 AM - 10:00 PM", "thursday": "10:30 AM - 08:00 PM", "friday": "10:30 AM - 08:00 PM", "saturday": "10:30 AM - 08:00 PM"}]},
{"source_id": 38, "location_name": "Hollywood", "url": "https://order.sweetgreen.com/hollywood/menu", "phone_number": "13234985558", "street_address_1": "6115 West Sunset Blvd", "street_address_2": "", "city": "Los Angeles", "postal_code": "90028", "state": "CA", "country": "US", "latitude": 34.098156, "longitude": -118.322591, "schedules": [{"sunday": "10:00 AM - 06:00 PM", "monday": "10:00 AM - 10:00 PM", "tuesday": "10:00 AM - 10:00 PM", "wednesday": "10:00 AM - 10:00 PM", "thursday": "10:00 AM - 04:00 PM", "friday": "10:00 AM - 06:00 PM", "saturday": "10:00 AM - 06:00 PM"}]},
{"source_id": 40, "location_name": "Union Square", "url": "https://order.sweetgreen.com/union-square/menu", "phone_number": "16466923131", "street_address_1": "8 E 18th St", "street_address_2": "", "city": "New York", "postal_code": "10003", "state": "NY", "country": "US", "latitude": 40.738069, "longitude": -73.991225, "schedules": [{"sunday": "10:30 AM - 03:00 PM", "monday": "10:30 AM - 10:00 PM", "tuesday": "10:30 AM - 10:00 PM", "wednesday": "10:30 AM - 10:00 PM", "thursday": "10:30 AM - 03:00 PM", "friday": "10:30 AM - 03:00 PM", "saturday": "10:30 AM - 03:00 PM"}]},
{"source_id": 8, "location_name": "College Park", "url": "https://order.sweetgreen.com/college-park/menu", "phone_number": "12407704443", "street_address_1": "8300 Baltimore Ave", "street_address_2": "", "city": "College Park", "postal_code": "20740", "state": "MD", "country": "US", "latitude": 38.992541, "longitude": -76.933663, "schedules": [{"sunday": "09:30 AM - 08:00 PM", "monday": "09:30 AM - 10:00 PM", "tuesday": "09:30 AM - 10:00 PM", "wednesday": "09:30 AM - 10:00 PM", "thursday": "09:30 AM - 03:00 PM", "friday": "09:30 AM - 08:00 PM", "saturday": "09:30 AM - 08:00 PM"}]},
{"source_id": 6, "location_name": "Foggy Bottom", "url": "https://order.sweetgreen.com/foggy-bottom/menu", "phone_number": "12029371412", "street_address_1": "2221 I St NW", "street_address_2": "", "city": "Washington", "postal_code": "20037", "state": "DC", "country": "US", "latitude": 38.901267, "longitude": -77.049277, "schedules": [{"sunday": "10:30 AM - 04:00 PM", "monday": "10:30 AM - 10:00 PM", "tuesday": "10:30 AM - 10:00 PM", "wednesday": "10:30 AM - 10:00 PM", "friday": "10:30 AM - 04:00 PM", "saturday": "10:30 AM - 04:00 PM"}]},
{"source_id": 39, "location_name": "Prudential Center", "url": "https://order.sweetgreen.com/prudential-center/menu", "phone_number": "18577534982", "street_address_1": "800 Boylston St", "street_address_2": "", "city": "Boston", "postal_code": "02199", "state": "MA", "country": "US", "latitude": 42.347522, "longitude": -71.081327, "schedules": [{"sunday": "10:30 AM - 08:00 PM", "monday": "09:30 AM - 10:00 PM", "tuesday": "09:30 AM - 10:00 PM", "wednesday": "09:30 AM - 10:00 PM", "thursday": "09:30 AM - 06:00 PM", "friday": "09:30 AM - 08:00 PM", "saturday": "10:30 AM - 08:00 PM"}]},
{"source_id": 42, "location_name": "Berkeley", "url": "https://order.sweetgreen.com/berkeley/menu", "phone_number": "15109908262", "street_address_1": "1890 Shattuck Ave", "street_address_2": "", "city": "Berkeley", "postal_code": "94709", "state": "CA", "country": "US", "latitude": 37.874013, "longitude": -122.268801, "schedules": [{"sunday": "10:00 AM - 07:00 PM", "monday": "10:00 AM - 08:00 PM", "tuesday": "10:00 AM - 08:00 PM", "wednesday": "10:00 AM - 08:00 PM", "thursday": "10:00 AM - 07:00 PM", "friday": "10:00 AM - 07:00 PM", "saturday": "10:00 AM - 07:00 PM"}]},
{"source_id": 43, "location_name": "Bleecker + 6th", "url": "https://order.sweetgreen.com/bleecker-6th/menu", "phone_number": "19176393212", "street_address_1": "226 Bleecker St", "street_address_2": "", "city": "New York", "postal_code": "10014", "state": "NY", "country": "US", "latitude": 40.730051, "longitude": -74.002506, "schedules": [{"sunday": "10:30 AM - 07:00 PM", "monday": "10:30 AM - 10:00 PM", "tuesday": "10:30 AM - 10:00 PM", "wednesday": "10:30 AM - 10:00 PM", "thursday": "10:30 AM - 07:00 PM", "friday": "10:30 AM - 07:00 PM", "saturday": "10:30 AM - 07:00 PM"}]},
{"source_id": 46, "location_name": "85th + 3rd", "url": "https://order.sweetgreen.com/85th-3rd/menu", "phone_number": "16466660860", "street_address_1": "1500 3rd Ave", "street_address_2": "", "city": "New York", "postal_code": "10028", "state": "NY", "country": "US", "latitude": 40.778024, "longitude": -73.954916, "schedules": [{"sunday": "10:30 AM - 10:00 PM", "monday": "10:30 AM - 10:00 PM", "tuesday": "10:30 AM - 10:00 PM", "wednesday": "10:30 AM - 10:00 PM", "thursday": "10:30 AM - 09:00 PM", "friday": "10:30 AM - 10:00 PM", "saturday": "10:30 AM - 10:00 PM"}]},
{"source_id": 47, "location_name": "Fenway", "url": "https://order.sweetgreen.com/fenway/menu", "phone_number": "18572332673", "street_address_1": "132 Brookline Ave", "street_address_2": "", "city": "Boston", "postal_code": "02215", "state": "MA", "country": "US", "latitude": 42.345051, "longitude": -71.10041, "schedules": [{"sunday": "10:30 AM - 09:00 PM", "monday": "09:30 AM - 10:00 PM", "tuesday": "09:30 AM - 10:00 PM", "wednesday": "09:30 AM - 10:00 PM", "thursday": "09:30 AM - 08:00 PM", "friday": "09:30 AM - 08:00 PM", "saturday": "10:30 AM - 09:00 PM"}]},
{"source_id": 41, "location_name": "Crystal City", "url": "https://order.sweetgreen.com/crystal-city/menu", "phone_number": "17036859089", "street_address_1": "2200 Crystal Dr, Ste E", "street_address_2": "", "city": "Arlington", "postal_code": "22202", "state": "VA", "country": "US", "latitude": 38.854301, "longitude": -77.050169, "schedules": [{"sunday": "10:30 AM - 04:00 PM", "monday": "10:30 AM - 10:00 PM", "tuesday": "10:30 AM - 10:00 PM", "wednesday": "10:30 AM - 10:00 PM", "friday": "10:30 AM - 04:00 PM", "saturday": "10:30 AM - 04:00 PM"}]},
{"source_id": 48, "location_name": "Clarendon", "url": "https://order.sweetgreen.com/clarendon/menu", "phone_number": "15712903956", "street_address_1": "3100 Clarendon Blvd", "street_address_2": "", "city": "Arlington", "postal_code": "22201", "state": "VA", "country": "US", "latitude": 38.8863, "longitude": -77.095381, "schedules": [{"sunday": "09:30 AM - 07:00 PM", "monday": "09:30 AM - 10:00 PM", "tuesday": "09:30 AM - 10:00 PM", "wednesday": "09:30 AM - 10:00 PM", "thursday": "09:30 AM - 03:00 PM", "friday": "09:30 AM - 07:00 PM", "saturday": "09:30 AM - 07:00 PM"}]},
{"source_id": 50, "location_name": "Astor Place", "url": "https://order.sweetgreen.com/astor-place/menu", "phone_number": "16466923112", "street_address_1": "10 Astor Pl", "street_address_2": "", "city": "New York", "postal_code": "10003", "state": "NY", "country": "US", "latitude": 40.729748, "longitude": -73.991698, "schedules": [{"sunday": "10:30 AM - 03:00 PM", "monday": "10:30 AM - 10:00 PM", "tuesday": "10:30 AM - 10:00 PM", "wednesday": "10:30 AM - 10:00 PM", "thursday": "10:30 AM - 05:00 PM", "friday": "10:30 AM - 03:00 PM", "saturday": "10:30 AM - 03:00 PM"}]},
{"source_id": 44, "location_name": "Downtown Crossing", "url": "https://order.sweetgreen.com/downtown-crossing/menu", "phone_number": "18579903191", "street_address_1": "13 School St", "street_address_2": "", "city": "Boston", "postal_code": "02108", "state": "MA", "country": "US", "latitude": 42.357699, "longitude": -71.058721, "schedules": [{"sunday": "10:30 AM - 03:00 PM", "monday": "09:30 AM - 08:00 PM", "tuesday": "09:30 AM - 08:00 PM", "wednesday": "09:30 AM - 08:00 PM", "friday": "09:30 AM - 04:00 PM", "saturday": "10:30 AM - 04:00 PM"}]},
{"source_id": 45, "location_name": "Palo Alto", "url": "https://order.sweetgreen.com/palo-alto/menu", "phone_number": "14152127385", "street_address_1": "581 Ramona St", "street_address_2": "", "city": "Palo Alto", "postal_code": "94301", "state": "CA", "country": "US", "latitude": 37.444811, "longitude": -122.160986, "schedules": [{"sunday": "10:30 AM - 08:00 PM", "monday": "10:30 AM - 09:00 PM", "tuesday": "10:30 AM - 09:00 PM", "wednesday": "10:30 AM - 09:00 PM", "thursday": "10:30 AM - 08:00 PM", "friday": "10:30 AM - 08:00 PM", "saturday": "10:30 AM - 08:00 PM"}]},
{"source_id": 51, "location_name": "River North", "url": "https://order.sweetgreen.com/river-north/menu", "phone_number": "13123748173", "street_address_1": "623 N State St", "street_address_2": "", "city": "Chicago", "postal_code": "60654", "state": "IL", "country": "US", "latitude": 41.893202, "longitude": -87.627954, "schedules": [{"sunday": "10:30 AM - 10:00 PM", "monday": "10:30 AM - 10:00 PM", "tuesday": "10:30 AM - 10:00 PM", "wednesday": "10:30 AM - 10:00 PM", "thursday": "10:30 AM - 04:00 PM", "friday": "10:30 AM - 10:00 PM", "saturday": "10:30 AM - 10:00 PM"}]},
{"source_id": 54, "location_name": "71st + 1st", "url": "https://order.sweetgreen.com/71st-1st/menu", "phone_number": "16465850900", "street_address_1": "1321 1st Ave", "street_address_2": "", "city": "New York", "postal_code": "10021", "state": "NY", "country": "US", "latitude": 40.767133, "longitude": -73.956837, "schedules": [{"sunday": "10:30 AM - 09:00 PM", "monday": "10:30 AM - 10:00 PM", "tuesday": "10:30 AM - 10:00 PM", "wednesday": "10:30 AM - 10:00 PM", "thursday": "10:30 AM - 08:00 PM", "friday": "10:30 AM - 09:00 PM", "saturday": "10:30 AM - 09:00 PM"}]},
{"source_id": 52, "location_name": "Meatpacking", "url": "https://order.sweetgreen.com/meatpacking/menu", "phone_number": "16468915100", "street_address_1": "32 Gansevoort St", "street_address_2": "", "city": "New York", "postal_code": "10014", "state": "NY", "country": "US", "latitude": 40.739191, "longitude": -74.005877, "schedules": [{"sunday": "10:30 AM - 06:00 PM", "monday": "10:30 AM - 10:00 PM", "tuesday": "10:30 AM - 10:00 PM", "wednesday": "10:30 AM - 10:00 PM", "thursday": "10:30 AM - 06:00 PM", "friday": "10:30 AM - 06:00 PM", "saturday": "10:30 AM - 06:00 PM"}]},
{"source_id": 49, "location_name": "Wall Street", "url": "https://order.sweetgreen.com/wall-street/menu", "phone_number": "12124879030", "street_address_1": "67 Wall St", "street_address_2": "", "city": "New York", "postal_code": "10005", "state": "NY", "country": "US", "latitude": 40.705547, "longitude": -74.008397, "schedules": [{"sunday": "09:30 AM - 04:00 PM", "monday": "09:30 AM - 10:00 PM", "tuesday": "09:30 AM - 10:00 PM", "wednesday": "09:30 AM - 10:00 PM", "thursday": "09:30 AM - 04:00 PM", "friday": "09:30 AM - 04:00 PM", "saturday": "09:30 AM - 04:00 PM"}]},
{"source_id": 55, "location_name": "Ink Block", "url": "https://order.sweetgreen.com/ink-block/menu", "phone_number": "16177120700", "street_address_1": "354 Harrison Ave", "street_address_2": "", "city": "Boston", "postal_code": "02118", "state": "MA", "country": "US", "latitude": 42.344586, "longitude": -71.063611, "schedules": [{"sunday": "10:30 AM - 08:00 PM", "monday": "09:30 AM - 10:00 PM", "tuesday": "09:30 AM - 10:00 PM", "wednesday": "09:30 AM - 10:00 PM", "thursday": "09:30 AM - 04:00 PM", "friday": "09:30 AM - 04:00 PM", "saturday": "10:30 AM - 08:00 PM"}]},
{"source_id": 53, "location_name": "KOP Mall", "url": "https://order.sweetgreen.com/kop-mall/menu", "phone_number": "16103120195", "street_address_1": "350 Mall Boulevard suite 3035", "street_address_2": "", "city": "King of Prussia", "postal_code": "19406", "state": "PA", "country": "US", "latitude": 40.090173, "longitude": -75.388973, "schedules": [{"sunday": "11:00 AM - 06:00 PM", "monday": "10:00 AM - 08:00 PM", "tuesday": "10:00 AM - 08:00 PM", "wednesday": "10:00 AM - 08:00 PM", "thursday": "10:00 AM - 07:00 PM", "friday": "10:00 AM - 09:00 PM", "saturday": "10:00 AM - 09:00 PM"}]},
{"source_id": 59, "location_name": "Pentagon City", "url": "https://order.sweetgreen.com/pentagon-city/menu", "phone_number": "17038881025", "street_address_1": "575 12th Rd South, Suite B2", "street_address_2": "", "city": "Arlington", "postal_code": "22202", "state": "VA", "country": "US", "latitude": 38.862262, "longitude": -77.056038, "schedules": [{"sunday": "10:30 AM - 08:00 PM", "monday": "10:30 AM - 10:00 PM", "tuesday": "10:30 AM - 10:00 PM", "wednesday": "10:30 AM - 10:00 PM", "thursday": "10:30 AM - 08:00 PM", "friday": "10:30 AM - 08:00 PM", "saturday": "10:30 AM - 08:00 PM"}]},
{"source_id": 58, "location_name": "Harvard Square", "url": "https://order.sweetgreen.com/harvard-square/menu", "phone_number": "16179413400", "street_address_1": "39 JFK St", "street_address_2": "", "city": "Cambridge", "postal_code": "02138", "state": "MA", "country": "US", "latitude": 42.372818, "longitude": -71.120173, "schedules": [{"sunday": "10:30 AM - 10:00 PM", "monday": "09:30 AM - 11:00 PM", "tuesday": "09:30 AM - 11:00 PM", "wednesday": "09:30 AM - 11:00 PM", "thursday": "09:30 AM - 09:00 PM", "friday": "09:30 AM - 09:00 PM", "saturday": "10:30 AM - 10:00 PM"}]},
{"source_id": 61, "location_name": "Farragut Square", "url": "https://order.sweetgreen.com/farragut-square/menu", "phone_number": "12025063079", "street_address_1": "888 17th St NW", "street_address_2": "", "city": "Washington", "postal_code": "20006", "state": "DC", "country": "US", "latitude": 38.901097, "longitude": -77.039899, "schedules": [{"monday": "10:30 AM - 10:00 PM", "tuesday": "10:30 AM - 10:00 PM", "wednesday": "10:30 AM - 10:00 PM"}]},
{"source_id": 60, "location_name": "Culver City: The Lab", "url": "https://order.sweetgreen.com/culver-city-the-lab/menu", "phone_number": "13106607471", "street_address_1": "8840 Washington Blvd", "street_address_2": "", "city": "Culver City", "postal_code": "90232", "state": "CA", "country": "US", "latitude": 34.027122, "longitude": -118.387316, "schedules": [{"sunday": "10:00 AM - 08:00 PM", "monday": "10:00 AM - 09:00 PM", "tuesday": "10:00 AM - 09:00 PM", "wednesday": "10:00 AM - 09:00 PM", "thursday": "10:00 AM - 06:00 PM", "friday": "10:00 AM - 08:00 PM", "saturday": "10:00 AM - 08:00 PM"}]},
{"source_id": 62, "location_name": "Brentwood", "url": "https://order.sweetgreen.com/brentwood/menu", "phone_number": "13108722422", "street_address_1": "11677 San Vicente Blvd", "street_address_2": "", "city": "Los Angeles", "postal_code": "90049", "state": "CA", "country": "US", "latitude": 34.053937, "longitude": -118.465178, "schedules": [{"sunday": "10:30 AM - 08:00 PM", "monday": "10:30 AM - 09:00 PM", "tuesday": "10:30 AM - 09:00 PM", "wednesday": "10:30 AM - 09:00 PM", "thursday": "10:30 AM - 07:00 PM", "friday": "10:30 AM - 08:00 PM", "saturday": "10:30 AM - 08:00 PM"}]},
{"source_id": 56, "location_name": "Soma", "url": "https://order.sweetgreen.com/soma/menu", "phone_number": "14158557653", "street_address_1": "171 2nd St", "street_address_2": "", "city": "San Francisco", "postal_code": "94105", "state": "CA", "country": "US", "latitude": 37.787285, "longitude": -122.3985, "schedules": [{"sunday": "10:00 AM - 06:00 PM", "monday": "10:00 AM - 08:00 PM", "tuesday": "10:00 AM - 08:00 PM", "wednesday": "10:00 AM - 08:00 PM", "thursday": "10:00 AM - 06:00 PM", "friday": "10:00 AM - 06:00 PM", "saturday": "10:00 AM - 06:00 PM"}]},
{"source_id": 57, "location_name": "Summer Street", "url": "https://order.sweetgreen.com/summer-street/menu", "phone_number": "16178704700", "street_address_1": "87 Summer St", "street_address_2": "", "city": "Boston", "postal_code": "02110", "state": "MA", "country": "US", "latitude": 42.353744, "longitude": -71.058429, "schedules": [{"sunday": "10:30 AM - 04:00 PM", "monday": "09:30 AM - 09:00 PM", "tuesday": "09:30 AM - 09:00 PM", "wednesday": "09:30 AM - 09:00 PM", "thursday": "09:30 AM - 04:00 PM", "friday": "09:30 AM - 04:00 PM", "saturday": "10:30 AM - 04:00 PM"}]},
{"source_id": 65, "location_name": "55th + Park", "url": "https://order.sweetgreen.com/55th-park/menu", "phone_number": "16468590100", "street_address_1": "60 E 55th St", "street_address_2": "", "city": "New York", "postal_code": "10022", "state": "NY", "country": "US", "latitude": 40.760525, "longitude": -73.972787, "schedules": [{"sunday": "10:30 AM - 03:00 PM", "monday": "10:30 AM - 10:00 PM", "tuesday": "10:30 AM - 10:00 PM", "wednesday": "10:30 AM - 10:00 PM", "thursday": "10:30 AM - 05:00 PM", "friday": "10:30 AM - 03:00 PM", "saturday": "10:30 AM - 03:00 PM"}]},
{"source_id": 70, "location_name": "DUMBO", "url": "https://order.sweetgreen.com/dumbo/menu", "phone_number": "13477574900", "street_address_1": "50 Washington St", "street_address_2": "", "city": "Brooklyn", "postal_code": "11201", "state": "NY", "country": "US", "latitude": 40.702854, "longitude": -73.989775, "schedules": [{"sunday": "10:30 AM - 07:00 PM", "monday": "10:30 AM - 10:00 PM", "tuesday": "10:30 AM - 10:00 PM", "wednesday": "10:30 AM - 10:00 PM", "thursday": "10:30 AM - 04:00 PM", "friday": "10:30 AM - 07:00 PM", "saturday": "10:30 AM - 07:00 PM"}]},
{"source_id": 63, "location_name": "61st + Lex", "url": "https://order.sweetgreen.com/61st-lex/menu", "phone_number": "16468591300", "street_address_1": "137 East 61st Street", "street_address_2": "", "city": "New York", "postal_code": "10065", "state": "NY", "country": "US", "latitude": 40.763679, "longitude": -73.967446, "schedules": [{"sunday": "10:30 AM - 06:00 PM", "monday": "10:30 AM - 10:00 PM", "tuesday": "10:30 AM - 10:00 PM", "wednesday": "10:30 AM - 10:00 PM", "thursday": "10:30 AM - 04:00 PM", "friday": "10:30 AM - 06:00 PM", "saturday": "10:30 AM - 06:00 PM"}]},
{"source_id": 64, "location_name": "Old Town", "url": "https://order.sweetgreen.com/old-town/menu", "phone_number": "15713190192", "street_address_1": "823 King St", "street_address_2": "", "city": "Alexandria", "postal_code": "22314", "state": "VA", "country": "US", "latitude": 38.805431, "longitude": -77.049042, "schedules": [{"sunday": "10:30 AM - 10:00 PM", "monday": "09:15 AM - 11:00 PM", "tuesday": "09:15 AM - 11:00 PM", "wednesday": "09:15 AM - 11:00 PM", "thursday": "09:15 AM - 09:00 PM", "friday": "09:15 AM - 10:00 PM", "saturday": "09:15 AM - 10:00 PM"}]},
{"source_id": 67, "location_name": "Mountain View", "url": "https://order.sweetgreen.com/mountain-view/menu", "phone_number": "16507537300", "street_address_1": "440 Castro St", "street_address_2": "", "city": "Mountain View", "postal_code": "94041", "state": "CA", "country": "US", "latitude": 37.390848, "longitude": -122.081017, "schedules": [{"sunday": "10:30 AM - 06:00 PM", "monday": "10:30 AM - 08:00 PM", "tuesday": "10:30 AM - 08:00 PM", "wednesday": "10:30 AM - 08:00 PM", "thursday": "10:30 AM - 04:00 PM", "friday": "10:30 AM - 04:00 PM", "saturday": "10:30 AM - 06:00 PM"}]},
{"source_id": 66, "location_name": "5th + Grand", "url": "https://order.sweetgreen.com/5th-grand/menu", "phone_number": "12132796900", "street_address_1": "601 W 5th St", "street_address_2": "", "city": "Los Angeles", "postal_code": "90071", "state": "CA", "country": "US", "latitude": 34.05073, "longitude": -118.25395, "schedules": [{"monday": "10:30 AM - 08:00 PM", "tuesday": "10:30 AM - 08:00 PM", "wednesday": "10:30 AM - 08:00 PM"}]},
{"source_id": 68, "location_name": "16th + Market", "url": "https://order.sweetgreen.com/16th-market/menu", "phone_number": "12154477200", "street_address_1": "1601 Market St", "street_address_2": "", "city": "Philadelphia", "postal_code": "19103", "state": "PA", "country": "US", "latitude": 39.953171, "longitude": -75.167332, "schedules": [{"monday": "09:30 AM - 09:00 PM", "tuesday": "09:30 AM - 09:00 PM", "wednesday": "09:30 AM - 09:00 PM"}]},
{"source_id": 69, "location_name": "Dearborn + Madison", "url": "https://order.sweetgreen.com/dearborn-madison/menu", "phone_number": "13125164300", "street_address_1": "1 N Dearborn St", "street_address_2": "", "city": "Chicago", "postal_code": "60602", "state": "IL", "country": "US", "latitude": 41.882203, "longitude": -87.629114, "schedules": [{"monday": "10:30 AM - 08:00 PM", "tuesday": "10:30 AM - 08:00 PM", "wednesday": "10:30 AM - 08:00 PM"}]},
{"source_id": 71, "location_name": "91st + Broadway", "url": "https://order.sweetgreen.com/91st-broadway/menu", "phone_number": "19179343200", "street_address_1": "2460 Broadway", "street_address_2": "", "city": "New York", "postal_code": "10025", "state": "NY", "country": "US", "latitude": 40.791443, "longitude": -73.973485, "schedules": [{"sunday": "10:30 AM - 08:00 PM", "monday": "10:30 AM - 10:00 PM", "tuesday": "10:30 AM - 10:00 PM", "wednesday": "10:30 AM - 10:00 PM", "thursday": "10:30 AM - 08:00 PM", "friday": "10:30 AM - 08:00 PM", "saturday": "10:30 AM - 08:00 PM"}]},
{"source_id": 74, "location_name": "Sunset Strip", "url": "https://order.sweetgreen.com/sunset-strip/menu", "phone_number": "13236885700", "street_address_1": "8570 Sunset Blvd", "street_address_2": "", "city": "West Hollywood", "postal_code": "90069", "state": "CA", "country": "US", "latitude": 34.092432, "longitude": -118.37848, "schedules": [{"sunday": "10:00 AM - 04:00 PM", "monday": "10:00 AM - 10:00 PM", "tuesday": "10:00 AM - 10:00 PM", "wednesday": "10:00 AM - 10:00 PM", "friday": "10:00 AM - 04:00 PM", "saturday": "10:00 AM - 04:00 PM"}]},
{"source_id": 75, "location_name": "CloudKitchen Test", "url": "https://order.sweetgreen.com/cloudkitchen-test/menu", "phone_number": "15055555555", "street_address_1": "26 Broadway", "street_address_2": "", "city": "New York", "postal_code": "10004", "state": "NY", "country": "US", "latitude": 40.7055092, "longitude": -74.0131178, "schedules": [{"sunday": "00:00 AM - 11:45 PM", "monday": "00:00 AM - 11:45 PM", "tuesday": "00:00 AM - 11:45 PM", "wednesday": "00:00 AM - 11:45 PM", "thursday": "00:00 AM - 11:45 PM", "friday": "00:00 AM - 11:45 PM", "saturday": "00:00 AM - 11:45 PM"}]},
{"source_id": 76, "location_name": "Sunnyvale", "url": "https://order.sweetgreen.com/sunnyvale/menu", "phone_number": "14157379900", "street_address_1": "300 W El Camino Real", "street_address_2": "", "city": "Sunnyvale", "postal_code": "94087", "state": "CA", "country": "US", "latitude": 37.368166, "longitude": -122.036101, "schedules": [{"sunday": "10:30 AM - 08:00 PM", "monday": "10:30 AM - 09:00 PM", "tuesday": "10:30 AM - 09:00 PM", "wednesday": "10:30 AM - 09:00 PM", "thursday": "10:30 AM - 08:00 PM", "friday": "10:30 AM - 08:00 PM", "saturday": "10:30 AM - 08:00 PM"}]},
{"source_id": 72, "location_name": "Rosslyn", "url": "https://order.sweetgreen.com/rosslyn/menu", "phone_number": "17033729009", "street_address_1": "1800 N Lynn St", "street_address_2": "", "city": "Arlington", "postal_code": "22209", "state": "VA", "country": "US", "latitude": 38.896399, "longitude": -77.071965, "schedules": [{"sunday": "10:30 AM - 04:00 PM", "monday": "10:30 AM - 10:00 PM", "tuesday": "10:30 AM - 10:00 PM", "wednesday": "10:30 AM - 10:00 PM", "thursday": "10:30 AM - 04:00 PM", "friday": "10:30 AM - 04:00 PM", "saturday": "10:30 AM - 04:00 PM"}]},
{"source_id": 79, "location_name": "12th + University", "url": "https://order.sweetgreen.com/12th-university/menu", "phone_number": "19178321900", "street_address_1": "101 University Pl", "street_address_2": "", "city": "New York", "postal_code": "10003", "state": "NY", "country": "US", "latitude": 40.73399, "longitude": -73.992409, "schedules": [{"sunday": "10:30 AM - 03:00 PM", "monday": "10:30 AM - 10:00 PM", "tuesday": "10:30 AM - 10:00 PM", "wednesday": "10:30 AM - 10:00 PM", "thursday": "10:30 AM - 05:00 PM", "friday": "10:30 AM - 03:00 PM", "saturday": "10:30 AM - 03:00 PM"}]},
{"source_id": 73, "location_name": "Georgetown", "url": "https://order.sweetgreen.com/georgetown/menu", "phone_number": "12028384300", "street_address_1": "1044 Wisconsin Ave NW", "street_address_2": "", "city": "Washington", "postal_code": "20007", "state": "DC", "country": "US", "latitude": 38.903842, "longitude": -77.063016, "schedules": [{"sunday": "09:30 AM - 08:00 PM", "monday": "09:30 AM - 10:00 PM", "tuesday": "09:30 AM - 10:00 PM", "wednesday": "09:30 AM - 10:00 PM", "thursday": "09:30 AM - 08:00 PM", "friday": "09:30 AM - 08:00 PM", "saturday": "09:30 AM - 08:00 PM"}]},
{"source_id": 78, "location_name": "Fulton Market", "url": "https://order.sweetgreen.com/fulton-market/menu", "phone_number": "13124710200", "street_address_1": "1000 Randolph St", "street_address_2": "", "city": "Chicago", "postal_code": "60607", "state": "IL", "country": "US", "latitude": 41.884615, "longitude": -87.652466, "schedules": [{"sunday": "10:30 AM - 10:00 PM", "monday": "10:30 AM - 10:00 PM", "tuesday": "10:30 AM - 10:00 PM", "wednesday": "10:30 AM - 10:00 PM", "thursday": "10:30 AM - 03:00 PM", "friday": "10:30 AM - 10:00 PM", "saturday": "10:30 AM - 10:00 PM"}]},
{"source_id": 77, "location_name": "Bryant Park", "url": "https://order.sweetgreen.com/bryant-park/menu", "phone_number": "19179935070", "street_address_1": "1114 6th Avenue", "street_address_2": "", "city": "New York", "postal_code": "10036", "state": "NY", "country": "US", "latitude": 40.754689, "longitude": -73.98266, "schedules": [{"sunday": "10:30 AM - 03:00 PM", "monday": "10:30 AM - 10:00 PM", "tuesday": "10:30 AM - 10:00 PM", "wednesday": "10:30 AM - 10:00 PM", "thursday": "10:30 AM - 05:00 PM", "friday": "10:30 AM - 03:00 PM", "saturday": "10:30 AM - 03:00 PM"}]},
{"source_id": 81, "location_name": "Millennium Park", "url": "https://order.sweetgreen.com/millennium-park/menu", "phone_number": "13124710300", "street_address_1": "150 N Michigan Ave", "street_address_2": "", "city": "Chicago", "postal_code": "60601", "state": "IL", "country": "US", "latitude": 41.884798, "longitude": -87.624953, "schedules": [{"sunday": "10:30 AM - 08:00 PM", "monday": "10:30 AM - 08:00 PM", "tuesday": "10:30 AM - 08:00 PM", "wednesday": "10:30 AM - 08:00 PM", "thursday": "10:30 AM - 03:00 PM", "friday": "10:30 AM - 04:00 PM", "saturday": "10:30 AM - 04:00 PM"}]},
{"source_id": 83, "location_name": "60 State", "url": "https://order.sweetgreen.com/60-state/menu", "phone_number": "16179968500", "street_address_1": "60 State St", "street_address_2": "", "city": "Boston", "postal_code": "02109", "state": "MA", "country": "US", "latitude": 42.359352, "longitude": -71.056392, "schedules": [{"sunday": "09:30 AM - 03:00 PM", "monday": "09:30 AM - 09:00 PM", "tuesday": "09:30 AM - 09:00 PM", "wednesday": "09:30 AM - 09:00 PM", "thursday": "09:30 AM - 04:00 PM", "friday": "09:30 AM - 04:00 PM", "saturday": "09:30 AM - 04:00 PM"}]},
{"source_id": 84, "location_name": "38th + Broadway", "url": "https://order.sweetgreen.com/38th-broadway/menu", "phone_number": "12123343020", "street_address_1": "1384 Broadway", "street_address_2": "", "city": "New York", "postal_code": "10021", "state": "NY", "country": "US", "latitude": 40.752571, "longitude": -73.987027, "schedules": [{"sunday": "10:30 AM - 04:00 PM", "monday": "10:30 AM - 10:00 PM", "tuesday": "10:30 AM - 10:00 PM", "wednesday": "10:30 AM - 10:00 PM", "thursday": "10:30 AM - 05:00 PM", "friday": "10:30 AM - 04:00 PM", "saturday": "10:30 AM - 04:00 PM"}]},
{"source_id": 88, "location_name": "San Mateo", "url": "https://order.sweetgreen.com/san-mateo/menu", "phone_number": "16507536500", "street_address_1": "1 East 3rd Ave", "street_address_2": "", "city": "San Mateo", "postal_code": "94401", "state": "CA", "country": "US", "latitude": 37.563241, "longitude": -122.325928, "schedules": [{"sunday": "10:00 AM - 07:00 PM", "monday": "10:00 AM - 08:00 PM", "tuesday": "10:00 AM - 08:00 PM", "wednesday": "10:00 AM - 08:00 PM", "thursday": "10:00 AM - 07:00 PM", "friday": "10:00 AM - 07:00 PM", "saturday": "10:00 AM - 07:00 PM"}]},
{"source_id": 82, "location_name": "Seaport Square", "url": "https://order.sweetgreen.com/seaport-square/menu", "phone_number": "16176168500", "street_address_1": "47 Northern Ave", "street_address_2": "", "city": "Boston", "postal_code": "02210", "state": "MA", "country": "US", "latitude": 42.352779, "longitude": -71.045803, "schedules": [{"sunday": "10:30 AM - 08:00 PM", "monday": "09:30 AM - 10:00 PM", "tuesday": "09:30 AM - 10:00 PM", "wednesday": "09:30 AM - 10:00 PM", "thursday": "09:30 AM - 04:00 PM", "friday": "09:30 AM - 04:00 PM", "saturday": "10:30 AM - 08:00 PM"}]},
{"source_id": 89, "location_name": "Legacy Place", "url": "https://order.sweetgreen.com/legacy-place/menu", "phone_number": "16178603500", "street_address_1": "244 Legacy Pl", "street_address_2": "", "city": "Dedham", "postal_code": "02026", "state": "MA", "country": "US", "latitude": 42.232695, "longitude": -71.179792, "schedules": [{"sunday": "10:30 AM - 09:00 PM", "monday": "10:30 AM - 10:00 PM", "tuesday": "10:30 AM - 10:00 PM", "wednesday": "10:30 AM - 10:00 PM", "thursday": "10:30 AM - 09:00 PM", "friday": "10:30 AM - 09:00 PM", "saturday": "10:30 AM - 09:00 PM"}]},
{"source_id": 85, "location_name": "Marina del Rey", "url": "https://order.sweetgreen.com/marina-del-rey/menu", "phone_number": "13103406880", "street_address_1": "4718 Admiralty Way", "street_address_2": "", "city": "Marina del Rey", "postal_code": "90292", "state": "CA", "country": "US", "latitude": 33.9794, "longitude": -118.439619, "schedules": [{"sunday": "10:30 AM - 10:00 PM", "monday": "10:30 AM - 10:00 PM", "tuesday": "10:30 AM - 10:00 PM", "wednesday": "10:30 AM - 10:00 PM", "thursday": "10:30 AM - 08:00 PM", "friday": "10:30 AM - 10:00 PM", "saturday": "10:30 AM - 10:00 PM"}]},
{"source_id": 86, "location_name": "Post Office Square", "url": "https://order.sweetgreen.com/post-office-square/menu", "phone_number": "16176485500", "street_address_1": "225 Franklin St", "street_address_2": "", "city": "Boston", "postal_code": "02210", "state": "MA", "country": "US", "latitude": 42.356197, "longitude": -71.054317, "schedules": [{"monday": "09:30 AM - 08:00 PM", "tuesday": "09:30 AM - 08:00 PM", "wednesday": "09:30 AM - 08:00 PM"}]},
{"source_id": 92, "location_name": "Wellesley", "url": "https://order.sweetgreen.com/wellesley/menu", "phone_number": "16179173500", "street_address_1": "180 Linden St", "street_address_2": "", "city": "Wellesley", "postal_code": "02482", "state": "MA", "country": "US", "latitude": 42.301084, "longitude": -71.292318, "schedules": [{"sunday": "10:30 AM - 08:00 PM", "monday": "09:30 AM - 10:00 PM", "tuesday": "09:30 AM - 10:00 PM", "wednesday": "09:30 AM - 10:00 PM", "thursday": "09:30 AM - 09:00 PM", "friday": "09:30 AM - 09:00 PM", "saturday": "10:30 AM - 09:00 PM"}]},
{"source_id": 90, "location_name": "La Brea", "url": "https://order.sweetgreen.com/la-brea/menu", "phone_number": "13103406050", "street_address_1": "180 S La Brea", "street_address_2": "", "city": "Los Angeles", "postal_code": "90036", "state": "CA", "country": "US", "latitude": 34.071269, "longitude": -118.343699, "schedules": [{"sunday": "10:00 AM - 09:00 PM", "monday": "10:00 AM - 10:00 PM", "tuesday": "10:00 AM - 10:00 PM", "wednesday": "10:00 AM - 10:00 PM", "thursday": "10:00 AM - 09:00 PM", "friday": "10:00 AM - 09:00 PM", "saturday": "10:00 AM - 09:00 PM"}]},
{"source_id": 91, "location_name": "Century City", "url": "https://order.sweetgreen.com/century-city/menu", "phone_number": "13106834650", "street_address_1": "10250 Santa Monica Blvd", "street_address_2": "", "city": "Los Angeles", "postal_code": "90067", "state": "CA", "country": "US", "latitude": 34.058603, "longitude": -118.419048, "schedules": [{"sunday": "10:30 AM - 07:00 PM", "monday": "10:30 AM - 08:00 PM", "tuesday": "10:30 AM - 08:00 PM", "wednesday": "10:30 AM - 08:00 PM", "thursday": "10:30 AM - 04:00 PM", "friday": "10:30 AM - 07:00 PM", "saturday": "10:30 AM - 07:00 PM"}]},
{"source_id": 104, "location_name": "8th + Hill", "url": "https://order.sweetgreen.com/8th-hill/menu", "phone_number": "12138949800", "street_address_1": "410 West 8th Street", "street_address_2": "", "city": "Los Angeles", "postal_code": "90014", "state": "CA", "country": "US", "latitude": 34.044712, "longitude": -118.256295, "schedules": [{"sunday": "10:00 AM - 08:00 PM", "monday": "10:00 AM - 09:00 PM", "tuesday": "10:00 AM - 09:00 PM", "wednesday": "10:00 AM - 09:00 PM", "thursday": "10:00 AM - 08:00 PM", "friday": "10:00 AM - 08:00 PM", "saturday": "10:00 AM - 08:00 PM"}]},
{"source_id": 106, "location_name": "West Adams Delivery Kitchen (RETIRED)", "url": "https://order.sweetgreen.com/west-adams-delivery-kitchen-retired/menu", "phone_number": "11111111111", "street_address_1": "8840 Washington Boulevard", "street_address_2": null, "city": "Culver City", "postal_code": "90232", "state": "CA", "country": "US", "latitude": 34.027176, "longitude": -118.387366, "schedules": [{}]},
{"source_id": 105, "location_name": "Hudson Yards", "url": "https://order.sweetgreen.com/hudson-yards/menu", "phone_number": "16468324350", "street_address_1": "10 Hudson Yards", "street_address_2": "", "city": "New York", "postal_code": "10001", "state": "NY", "country": "US", "latitude": 40.752599, "longitude": -74.001377, "schedules": [{"sunday": "10:30 AM - 04:00 PM", "monday": "10:30 AM - 10:00 PM", "tuesday": "10:30 AM - 10:00 PM", "wednesday": "10:30 AM - 10:00 PM", "thursday": "10:30 AM - 03:00 PM", "friday": "10:30 AM - 04:00 PM", "saturday": "10:30 AM - 04:00 PM"}]},
{"source_id": 139, "location_name": "Court + Atlantic", "url": "https://order.sweetgreen.com/court-atlantic/menu", "phone_number": "13477676800", "street_address_1": "127 Court St", "street_address_2": "", "city": "Brooklyn", "postal_code": "11201", "state": "NY", "country": "US", "latitude": 40.689497, "longitude": -73.992257, "schedules": [{"sunday": "10:30 AM - 09:00 PM", "monday": "10:30 AM - 10:00 PM", "tuesday": "10:30 AM - 10:00 PM", "wednesday": "10:30 AM - 10:00 PM", "thursday": "10:30 AM - 09:00 PM", "friday": "10:30 AM - 09:00 PM", "saturday": "10:30 AM - 09:00 PM"}]},
{"source_id": 146, "location_name": "Montana Ave", "url": "https://order.sweetgreen.com/montana-ave/menu", "phone_number": "13104558813", "street_address_1": "1517 Montana Ave", "street_address_2": "", "city": "Santa Monica", "postal_code": "90402", "state": "CA", "country": "US", "latitude": 34.033355, "longitude": -118.493997, "schedules": [{"sunday": "10:30 AM - 07:00 PM", "monday": "10:30 AM - 09:00 PM", "tuesday": "10:30 AM - 09:00 PM", "wednesday": "10:30 AM - 09:00 PM", "thursday": "10:30 AM - 03:00 PM", "friday": "10:30 AM - 07:00 PM", "saturday": "10:30 AM - 07:00 PM"}]},
{"source_id": 182, "location_name": "Pike + Rose", "url": "https://order.sweetgreen.com/pike-rose/menu", "phone_number": "13014337600", "street_address_1": "11875 Grand Park Ave", "street_address_2": "", "city": "North Bethesda", "postal_code": "20852", "state": "MD", "country": "US", "latitude": 39.050524, "longitude": -77.117196, "schedules": [{"sunday": "09:30 AM - 08:00 PM", "monday": "09:30 AM - 10:00 PM", "tuesday": "09:30 AM - 10:00 PM", "wednesday": "09:30 AM - 10:00 PM", "thursday": "09:30 AM - 04:00 PM", "friday": "09:30 AM - 08:00 PM", "saturday": "09:30 AM - 08:00 PM"}]},
{"source_id": 189, "location_name": "Demo Five", "url": "https://order.sweetgreen.com/demo-five/menu", "phone_number": "15555555555", "street_address_1": "4718 Admiralty Way", "street_address_2": "", "city": "Marina del Rey", "postal_code": "90292", "state": "CA", "country": "US", "latitude": 33.979434, "longitude": -118.43954, "schedules": [{"sunday": "00:00 AM - 11:45 PM", "monday": "00:00 AM - 11:45 PM", "tuesday": "00:00 AM - 11:45 PM", "wednesday": "00:00 AM - 11:45 PM", "thursday": "00:00 AM - 11:45 PM", "friday": "00:00 AM - 11:45 PM", "saturday": "00:00 AM - 11:45 PM"}]},
{"source_id": 187, "location_name": "Demo Four", "url": "https://order.sweetgreen.com/demo-four/menu", "phone_number": "16464498884", "street_address_1": "168 E Broadway", "street_address_2": "", "city": "New York", "postal_code": "10002", "state": "NY", "country": "US", "latitude": 40.7140657, "longitude": -73.9900561, "schedules": [{"sunday": "00:00 AM - 11:45 PM", "monday": "00:00 AM - 11:45 PM", "tuesday": "00:00 AM - 11:45 PM", "wednesday": "00:00 AM - 11:45 PM", "thursday": "00:00 AM - 11:45 PM", "friday": "00:00 AM - 11:45 PM", "saturday": "00:00 AM - 11:45 PM"}]},
{"source_id": 213, "location_name": "Studio City", "url": "https://order.sweetgreen.com/studio-city/menu", "phone_number": "18189626400", "street_address_1": "13003 Ventura Blvd", "street_address_2": "", "city": "Studio City", "postal_code": "91604", "state": "CA", "country": "US", "latitude": 34.145879, "longitude": -118.416332, "schedules": [{"sunday": "10:00 AM - 09:00 PM", "monday": "10:00 AM - 10:00 PM", "tuesday": "10:00 AM - 10:00 PM", "wednesday": "10:00 AM - 10:00 PM", "thursday": "10:00 AM - 04:00 PM", "friday": "10:00 AM - 09:00 PM", "saturday": "10:00 AM - 09:00 PM"}]},
{"source_id": 224, "location_name": "WeWork 79 Madison Ave (Retired)", "url": "https://order.sweetgreen.com/wework-79-madison-ave-retired/menu", "phone_number": "16464498884", "street_address_1": "79 Madison Ave", "street_address_2": "", "city": "New York", "postal_code": "10016", "state": "NY", "country": "US", "latitude": 40.7440943, "longitude": -73.9853103, "schedules": [{"monday": "12:30 PM - 01:00 PM", "tuesday": "12:30 PM - 01:00 PM", "wednesday": "12:30 PM - 01:00 PM", "thursday": "12:30 PM - 01:00 PM", "friday": "12:30 PM - 01:00 PM"}]},
{"source_id": 230, "location_name": "West Coast NRO", "url": "https://order.sweetgreen.com/west-coast-nro/menu", "phone_number": "14247448321", "street_address_1": "3021 Airport Avenue", "street_address_2": "", "city": "Santa Monica", "postal_code": "90405", "state": "CA", "country": "US", "latitude": 34.01417, "longitude": -118.449684, "schedules": [{}]},
{"source_id": 238, "location_name": "Chambers St", "url": "https://order.sweetgreen.com/chambers-st/menu", "phone_number": "19179830200", "street_address_1": "125 Chambers St", "street_address_2": "", "city": "New York", "postal_code": "10007", "state": "NY", "country": "US", "latitude": 40.715543, "longitude": -74.008808, "schedules": [{"sunday": "09:30 AM - 06:00 PM", "monday": "09:30 AM - 10:00 PM", "tuesday": "09:30 AM - 10:00 PM", "wednesday": "09:30 AM - 10:00 PM", "thursday": "09:30 AM - 06:00 PM", "friday": "09:30 AM - 06:00 PM", "saturday": "09:30 AM - 06:00 PM"}]},
{"source_id": 239, "location_name": "Soma Delivery Kitchen (RETIRED)", "url": "https://order.sweetgreen.com/soma-delivery-kitchen-retired/menu", "phone_number": "14159961500", "street_address_1": "475 Sixth St.", "street_address_2": "", "city": "San Francisco", "postal_code": "94103", "state": "CA", "country": "US", "latitude": 37.776576, "longitude": -122.402602, "schedules": [{}]},
{"source_id": 249, "location_name": "Montrose", "url": "https://order.sweetgreen.com/montrose/menu", "phone_number": "18327206500", "street_address_1": "1303 Westheimer", "street_address_2": "", "city": "Houston", "postal_code": "77006", "state": "TX", "country": "US", "latitude": 29.743436, "longitude": -95.395113, "schedules": [{"sunday": "10:30 AM - 09:00 PM", "monday": "10:30 AM - 09:00 PM", "tuesday": "10:30 AM - 09:00 PM", "wednesday": "10:30 AM - 09:00 PM", "friday": "10:30 AM - 08:00 PM", "saturday": "10:30 AM - 09:00 PM"}]},
{"source_id": 254, "location_name": "Rice Village", "url": "https://order.sweetgreen.com/rice-village/menu", "phone_number": "18327207500", "street_address_1": "2551 Amherst St", "street_address_2": "", "city": "Houston", "postal_code": "77005", "state": "TX", "country": "US", "latitude": 29.715718, "longitude": -95.418101, "schedules": [{"sunday": "10:30 AM - 09:00 PM", "monday": "10:30 AM - 10:00 PM", "tuesday": "10:30 AM - 10:00 PM", "wednesday": "10:30 AM - 10:00 PM", "friday": "10:30 AM - 08:00 PM", "saturday": "10:30 AM - 09:00 PM"}]},
{"source_id": 274, "location_name": "32nd + Park", "url": "https://order.sweetgreen.com/32nd-park/menu", "phone_number": "19179701900", "street_address_1": "2 Park Ave", "street_address_2": "", "city": "New York", "postal_code": "10016", "state": "NY", "country": "US", "latitude": 40.746332, "longitude": -73.982599, "schedules": [{"sunday": "10:30 AM - 03:00 PM", "monday": "10:30 AM - 10:00 PM", "tuesday": "10:30 AM - 10:00 PM", "wednesday": "10:30 AM - 10:00 PM", "thursday": "10:30 AM - 05:00 PM", "friday": "10:30 AM - 03:00 PM", "saturday": "10:30 AM - 03:00 PM"}]},
{"source_id": 278, "location_name": "River North Delivery Kitchen (RETIRED)", "url": "https://order.sweetgreen.com/river-north-delivery-kitchen-retired/menu", "phone_number": "16264363500", "street_address_1": "820 N Orleans St.", "street_address_2": "", "city": "Chicago", "postal_code": "60610", "state": "IL", "country": "US", "latitude": 41.897276, "longitude": -87.637328, "schedules": [{}]},
{"source_id": 280, "location_name": "Rockefeller Center", "url": "https://order.sweetgreen.com/rockefeller-center/menu", "phone_number": "16468914200", "street_address_1": "30 Rockefeller Plaza", "street_address_2": "", "city": "New York", "postal_code": "10112", "state": "NY", "country": "US", "latitude": 40.759152, "longitude": -73.979642, "schedules": [{"sunday": "10:30 AM - 03:00 PM", "monday": "10:30 AM - 10:00 PM", "tuesday": "10:30 AM - 10:00 PM", "wednesday": "10:30 AM - 10:00 PM", "thursday": "10:30 AM - 05:00 PM", "friday": "10:30 AM - 03:00 PM", "saturday": "10:30 AM - 03:00 PM"}]},
{"source_id": 277, "location_name": "Grand Central", "url": "https://order.sweetgreen.com/grand-central/menu", "phone_number": "19179702300", "street_address_1": "230 Park Avenue", "street_address_2": "", "city": "New York", "postal_code": "10169", "state": "NY", "country": "US", "latitude": 40.754428, "longitude": -73.976193, "schedules": [{"sunday": "10:30 AM - 03:00 PM", "monday": "10:30 AM - 10:00 PM", "tuesday": "10:30 AM - 10:00 PM", "wednesday": "10:30 AM - 10:00 PM", "thursday": "10:30 AM - 04:00 PM", "friday": "10:30 AM - 03:00 PM", "saturday": "10:30 AM - 03:00 PM"}]},
{"source_id": 284, "location_name": "Penn Quarter", "url": "https://order.sweetgreen.com/penn-quarter/menu", "phone_number": "12028042250", "street_address_1": "624 E. Street, NW", "street_address_2": "", "city": "Washington", "postal_code": "20004", "state": "DC", "country": "US", "latitude": 38.895998, "longitude": -77.02066, "schedules": [{"sunday": "10:30 AM - 03:00 PM", "monday": "10:30 AM - 10:00 PM", "tuesday": "10:30 AM - 10:00 PM", "wednesday": "10:30 AM - 10:00 PM", "thursday": "10:30 AM - 04:00 PM", "friday": "10:30 AM - 04:00 PM", "saturday": "10:30 AM - 03:00 PM"}]},
{"source_id": 286, "location_name": "Murray Hill", "url": "https://order.sweetgreen.com/murray-hill/menu", "phone_number": "19178105800", "street_address_1": "606 1st Ave", "street_address_2": "", "city": "New York", "postal_code": "10016", "state": "NY", "country": "US", "latitude": 40.743839, "longitude": -73.972535, "schedules": [{"sunday": "10:30 AM - 09:00 PM", "monday": "09:30 AM - 10:00 PM", "tuesday": "09:30 AM - 10:00 PM", "wednesday": "09:30 AM - 10:00 PM", "thursday": "09:30 AM - 08:00 PM", "friday": "09:30 AM - 09:00 PM", "saturday": "10:30 AM - 09:00 PM"}]},
{"source_id": 287, "location_name": "30 Vandam Delivery Kitchen (RETIRED)", "url": "https://order.sweetgreen.com/30-vandam-delivery-kitchen-retired/menu", "phone_number": "16466307900", "street_address_1": "175 Varick Street", "street_address_2": "", "city": "New York", "postal_code": "10014", "state": "NY", "country": "US", "latitude": 40.727693, "longitude": -74.005632, "schedules": [{}]},
{"source_id": 293, "location_name": "Silver Lake", "url": "https://order.sweetgreen.com/silver-lake/menu", "phone_number": "13238706800", "street_address_1": "3925 Sunset Blvd", "street_address_2": "", "city": "Los Angeles", "postal_code": "90029", "state": "CA", "country": "US", "latitude": 34.092609, "longitude": -118.280097, "schedules": [{"sunday": "10:00 AM - 10:00 PM", "monday": "10:00 AM - 10:00 PM", "tuesday": "10:00 AM - 10:00 PM", "wednesday": "10:00 AM - 10:00 PM", "thursday": "10:00 AM - 08:00 PM", "friday": "10:00 AM - 10:00 PM", "saturday": "10:00 AM - 10:00 PM"}]},
{"source_id": 364, "location_name": "Early Experience LAB", "url": "https://order.sweetgreen.com/early-experience-lab/menu", "phone_number": "12135662171", "street_address_1": "8919 Ellis Avenue", "street_address_2": "", "city": "Los Angeles", "postal_code": "90034", "state": "CA", "country": "US", "latitude": 34.029359, "longitude": -118.389253, "schedules": [{"sunday": "00:00 AM - 11:45 PM", "monday": "00:00 AM - 11:45 PM", "tuesday": "00:00 AM - 11:45 PM", "wednesday": "00:00 AM - 11:45 PM", "thursday": "00:00 AM - 11:45 PM", "friday": "00:00 AM - 11:45 PM", "saturday": "00:00 AM - 11:45 PM"}]},
{"source_id": 407, "location_name": "Hollywood Delivery Kitchen (RETIRED)", "url": "https://order.sweetgreen.com/hollywood-delivery-kitchen-retired/menu", "phone_number": "12139557030", "street_address_1": "615 North Western Avenue", "street_address_2": null, "city": "Los Angeles", "postal_code": "90004", "state": "CA", "country": "US", "latitude": 34.082225, "longitude": -118.309478, "schedules": [{}]}
]
